cacheutils/__init__.py
cacheutils/aerospike.py
cacheutils/hbase.py
cacheutils/utils.py
cacheutils-0.1.1.dist-info/DESCRIPTION.rst
cacheutils-0.1.1.dist-info/METADATA
cacheutils-0.1.1.dist-info/RECORD
cacheutils-0.1.1.dist-info/WHEEL
cacheutils-0.1.1.dist-info/metadata.json
cacheutils-0.1.1.dist-info/top_level.txt
