Metadata-Version: 2.0
Name: cacheutils
Version: 0.1.1
Summary: A bunch of cache utils.
Home-page: UNKNOWN
Author: Nicolás Ramírez
Author-email: nramirez.uy@gmail.com
License: BSD
Platform: UNKNOWN
Classifier: Intended Audience :: Developers
Classifier: License :: OSI Approved :: BSD License
Classifier: Operating System :: OS Independent
Classifier: Programming Language :: Python
Classifier: Programming Language :: Python :: 2
Classifier: Programming Language :: Python :: 2.7
Classifier: Topic :: Software Development :: Libraries :: Python Modules
Requires-Dist: cachetools
Requires-Dist: w3lib
Provides-Extra: aerospike
Requires-Dist: aerospike; extra == 'aerospike'
Provides-Extra: hbase
Requires-Dist: happybase; extra == 'hbase'
